generate_graphene/__init__.py
generate_graphene/config.py
generate_graphene/generate_graphene.py
generate_graphene/utils.py
generate_graphene-0.2.4.dist-info/METADATA
generate_graphene-0.2.4.dist-info/WHEEL
generate_graphene-0.2.4.dist-info/top_level.txt
generate_graphene-0.2.4.dist-info/RECORD
